co2114/__init__.py
co2114/engine.py
co2114/agent/__init__.py
co2114/agent/environment.py
co2114/agent/things.py
co2114/constraints/__init__.py
co2114/constraints/magic.py
co2114/constraints/sudoku.py
co2114/constraints/csp/__init__.py
co2114/constraints/csp/util.py
co2114/optimisation/__init__.py
co2114/optimisation/minimax.py
co2114/optimisation/planning.py
co2114/optimisation/things.py
co2114/reasoning/__init__.py
co2114/reasoning/cluedo.py
co2114/reasoning/inference.py
co2114/reasoning/logic.py
co2114/search/__init__.py
co2114/search/graph.py
co2114/search/maze.py
co2114/search/things.py
co2114/search/util.py
co2114/util/__init__.py
co2114/util/colours.py
co2114/util/fonts.py
co2114-2026.1.2.dist-info/licenses/LICENSE
co2114-2026.1.2.dist-info/METADATA
co2114-2026.1.2.dist-info/WHEEL
co2114-2026.1.2.dist-info/top_level.txt
co2114-2026.1.2.dist-info/RECORD
