Metadata-Version: 2.4
Name: co2114
Version: 2026.1.2
Summary: codebase for co2114
Author: wil ward
Requires-Python: >=3.12
License-File: LICENSE
Requires-Dist: pygame>=2.6
Requires-Dist: numpy
Requires-Dist: ipython
Requires-Dist: matplotlib
Requires-Dist: jupyter
Requires-Dist: scikit-learn
Requires-Dist: seaborn
Dynamic: author
Dynamic: license-file
Dynamic: requires-dist
Dynamic: requires-python
Dynamic: summary
